Metadata-Version: 2.1
Name: zip-import
Version: 0.0.1
Summary: Load module from zip 
Home-page: https://github.com/cn-kali-team/zip_import
Author: Kali-Team
Author-email: root@kali-team.cn
License: MIT
Platform: UNKNOWN
Classifier: License :: OSI Approved :: MIT License
Classifier: Programming Language :: Python
Classifier: Programming Language :: Python :: 3
Classifier: Programming Language :: Python :: 3.6
Classifier: Programming Language :: Python :: Implementation :: CPython
Classifier: Programming Language :: Python :: Implementation :: PyPy
Requires-Python: >=3.6.0
